LICENSE
MANIFEST.in
README.rst
setup.py
bkash/__init__.py
bkash/admin.py
bkash/apps.py
bkash/managers.py
bkash/models.py
bkash/tests.py
bkash/urls.py
bkash/utils.py
bkash/views.py
bkash/migrations/0001_initial.py
bkash/migrations/__init__.py
django_bkash_integration.egg-info/PKG-INFO
django_bkash_integration.egg-info/SOURCES.txt
django_bkash_integration.egg-info/dependency_links.txt
django_bkash_integration.egg-info/requires.txt
django_bkash_integration.egg-info/top_level.txt