Metadata-Version: 1.1
Name: django-bkash-integration
Version: 0.3
Summary: A simple django app to integrate bkash rest api to your application
Home-page: https://github.com/Taitalus/django-bkash-integration
Author: Raju Ahmed Shetu
Author-email: shetu2153@gmail.com
License: BSD License
Platform: UNKNOWN
Classifier: Environment :: Web Environment
Classifier: Framework :: Django
Classifier: Framework :: Django :: 2.0
Classifier: Intended Audience :: Developers
Classifier: License :: OSI Approved :: BSD License
Classifier: Operating System :: OS Independent
Classifier: Programming Language :: Python
Classifier: Programming Language :: Python :: 3.5
Classifier: Programming Language :: Python :: 3.6
Classifier: Topic :: Internet :: WWW/HTTP
Classifier: Topic :: Internet :: WWW/HTTP :: Dynamic Content
